dotcoin/__init__.py
dotcoin/__main__.py
dotcoin/console/__init__.py
dotcoin/console/actions.py
dotcoin/console/parser.py
dotcoin/context/__init__.py
dotcoin/context/fetch.py
dotcoin/context/match.py
dotcoin/context/source.py
dotcoin/core/__init__.py
dotcoin/core/abstract.py
dotcoin/core/error.py
dotcoin/core/types.py
dotcoin/queries/__init__.py
dotcoin/queries/common.py
dotcoin/queries/index.py
dotcoin/queries/markets.py
dotcoin/queries/utility.py
dotcoin/sources/__init__.py
dotcoin/sources/ccxt/__init__.py
dotcoin/sources/ccxt/exchange.py
dotcoin/sources/ccxt/source.py
dotcoin/sources/ccxt/utility.py
dotcoin/tables/__init__.py
dotcoin/tables/book.py
dotcoin/tables/index.py
dotcoin/tables/ticker.py
dotcoin/tables/utility.py
dotcoin-0.1.0.dist-info/entry_points.txt
dotcoin-0.1.0.dist-info/LICENSE
dotcoin-0.1.0.dist-info/WHEEL
dotcoin-0.1.0.dist-info/METADATA
dotcoin-0.1.0.dist-info/RECORD
