Metadata-Version: 2.1
Name: dotcoin
Version: 0.1.0
Summary: 
Home-page: https://github.com/oroschz/dotcoin
License: MIT
Author: Orlando Ospino Sánchez
Author-email: oroschz@outlook.com
Requires-Python: >=3.7,<4.0
Classifier: License :: OSI Approved :: MIT License
Classifier: Programming Language :: Python :: 3
Classifier: Programming Language :: Python :: 3.7
Classifier: Programming Language :: Python :: 3.8
Classifier: Programming Language :: Python :: 3.9
Requires-Dist: beautifultable (>=1.0.1,<2.0.0)
Requires-Dist: ccxt (>=1.47.3,<2.0.0)
Requires-Dist: six (>=1.15.0,<2.0.0)
Project-URL: Repository, https://github.com/oroschz/dotcoin
